{"name":"Roblox_Lapskaus","className":"DataModel","filePaths":["default.project.json"],"children":[{"name":"Lighting","className":"Lighting"},{"name":"ReplicatedStorage","className":"ReplicatedStorage","children":[{"name":"Assets","className":"Folder","children":[{"name":"Lapskaus","className":"Folder","children":[{"name":"BlueLapskaus","className":"Model","filePaths":["src/ReplicatedStorage\\Assets\\Lapskaus\\BlueLapskaus.rbxm"],"children":[{"name":"Surface","className":"Part"},{"name":"Lapskaus","className":"Part"}]},{"name":"RedLapskaus","className":"Model","filePaths":["src/ReplicatedStorage\\Assets\\Lapskaus\\RedLapskaus.rbxm"],"children":[{"name":"Surface","className":"Part"},{"name":"Lapskaus","className":"Part"}]}]}]},{"name":"Config","className":"Folder","children":[{"name":"MovementConfig","className":"ModuleScript","filePaths":["src/ReplicatedStorage\\Config\\MovementConfig.luau"]},{"name":"WeaponConfig","className":"ModuleScript","filePaths":["src/ReplicatedStorage\\Config\\WeaponConfig.luau"]}]},{"name":"Events","className":"Folder","children":[{"name":"CaptureLapskaus","className":"RemoteEvent","filePaths":["src/ReplicatedStorage\\Events\\CaptureLapskaus.rbxm"]},{"name":"FireWeapon","className":"RemoteEvent","filePaths":["src/ReplicatedStorage\\Events\\FireWeapon.rbxm"]},{"name":"GivePlayerLapskaus","className":"RemoteEvent","filePaths":["src/ReplicatedStorage\\Events\\GivePlayerLapskaus.rbxm"]},{"name":"KillPlayer","className":"RemoteEvent","filePaths":["src/ReplicatedStorage\\Events\\KillPlayer.rbxm"]},{"name":"RespawnPlayer","className":"RemoteEvent","filePaths":["src/ReplicatedStorage\\Events\\RespawnPlayer.rbxm"]},{"name":"TimerUpdated","className":"UnreliableRemoteEvent","filePaths":["src/ReplicatedStorage\\Events\\TimerUpdated.rbxm"]}]},{"name":"GameObjectsScripts","className":"Folder","children":[{"name":"Lapskaus","className":"Script","filePaths":["src/ReplicatedStorage\\GameObjectsScripts\\Lapskaus.server.luau"]}]},{"name":"Modules","className":"Folder","children":[{"name":"Client","className":"ModuleScript","filePaths":["src/ReplicatedStorage\\Modules\\Client.luau"]}]},{"name":"Types","className":"Folder","children":[{"name":"Server","className":"ModuleScript","filePaths":["src/ReplicatedStorage\\Types\\Server.luau"]}]},{"name":"Weapons","className":"Folder","children":[{"name":"TestGun","className":"Model","filePaths":["src/ReplicatedStorage\\Weapons\\TestGun.rbxm"],"children":[{"name":"Barrel","className":"Part"},{"name":"Handle","className":"Part"}]}]},{"name":"viewmodel","className":"Model","filePaths":["src/ReplicatedStorage\\viewmodel.rbxm"],"children":[{"name":"AnimationController","className":"AnimationController"},{"name":"LeftArm","className":"MeshPart"},{"name":"CameraBone","className":"MeshPart","children":[{"name":"CameraBone","className":"Motor6D"}]},{"name":"HumanoidRootPart","className":"MeshPart","children":[{"name":"RightArm","className":"Motor6D"},{"name":"LeftArm","className":"Motor6D"}]},{"name":"RightArm","className":"MeshPart"}]},{"name":"Enums","className":"Folder","children":[{"name":"Global","className":"ModuleScript","filePaths":["src/ReplicatedStorage\\Enums\\Global.luau"]}]},{"name":"UI","className":"Folder","children":[{"name":"TestMain","className":"Folder","children":[{"name":"TestMain","className":"ScreenGui","filePaths":["src/ReplicatedStorage\\UI\\TestMain\\TestMain.rbxm"],"children":[{"name":"Timer","className":"TextLabel"},{"name":"PlayerInfo","className":"Frame","children":[{"name":"ImageLabel","className":"ImageLabel"},{"name":"UIGridLayout","className":"UIGridLayout"},{"name":"TextLabel","className":"TextLabel"}]}]},{"name":"TestUI","className":"LocalScript","filePaths":["src/ReplicatedStorage\\UI\\TestMain\\TestUI.client.luau"]}]}]}]},{"name":"ServerScriptService","className":"ServerScriptService","children":[{"name":"Game","className":"Script","filePaths":["src/ServerScriptService\\Game.server.luau"]},{"name":"WeaponHandler","className":"Script","filePaths":["src/ServerScriptService\\WeaponHandler.server.luau"]},{"name":"Modules","className":"Folder","children":[{"name":"GamemodeHandler","className":"ModuleScript","filePaths":["src/ServerScriptService\\Modules\\GamemodeHandler.luau"]},{"name":"LapskausSetup","className":"ModuleScript","filePaths":["src/ServerScriptService\\Modules\\LapskausSetup.luau"]},{"name":"PlayerKillHandler","className":"ModuleScript","filePaths":["src/ServerScriptService\\Modules\\PlayerKillHandler.luau"]},{"name":"RespawnHandler","className":"ModuleScript","filePaths":["src/ServerScriptService\\Modules\\RespawnHandler.luau"]},{"name":"Gamemodes","className":"Folder","children":[{"name":"CaptureTheLapskaus","className":"ModuleScript","filePaths":["src/ServerScriptService\\Modules\\Gamemodes\\CaptureTheLapskaus.luau"]},{"name":"Deathmatch","className":"ModuleScript","filePaths":["src/ServerScriptService\\Modules\\Gamemodes\\Deathmatch.luau"]}]}]}]},{"name":"ServerStorage","className":"ServerStorage","children":[{"name":"ServerEvents","className":"Folder","children":[{"name":"RequestKill","className":"BindableEvent","filePaths":["src/ServerStorage\\ServerEvents\\RequestKill.rbxm"]},{"name":"RequestLapskaus","className":"BindableFunction","filePaths":["src/ServerStorage\\ServerEvents\\RequestLapskaus.rbxm"]}]}]},{"name":"SoundService","className":"SoundService"},{"name":"StarterPlayer","className":"StarterPlayer","children":[{"name":"StarterCharacterScripts","className":"StarterCharacterScripts","children":[{"name":"ClientController","className":"LocalScript","filePaths":["src/StarterPlayer/StarterCharacterScripts\\ClientController.client.luau"]},{"name":"WeaponController","className":"LocalScript","filePaths":["src/StarterPlayer/StarterCharacterScripts\\WeaponController.client.luau"]},{"name":"UI","className":"LocalScript","filePaths":["src/StarterPlayer/StarterCharacterScripts\\UI.client.luau"]}]},{"name":"StarterPlayerScripts","className":"StarterPlayerScripts"}]},{"name":"Workspace","className":"Workspace","children":[{"name":"Baseplate","className":"Part"}]}]}